cern_sso-0.1.1.dist-info/DESCRIPTION.rst
cern_sso-0.1.1.dist-info/METADATA
cern_sso-0.1.1.dist-info/metadata.json
cern_sso-0.1.1.dist-info/pbr.json
cern_sso-0.1.1.dist-info/RECORD
cern_sso-0.1.1.dist-info/top_level.txt
cern_sso-0.1.1.dist-info/WHEEL
cernsso/__init__.py
cernsso/cookie.py
