Metadata-Version: 2.0
Name: cern-sso
Version: 0.1.1
Summary: Python wrapper around cern-get-sso-cookie
Home-page: https://github.com/scr4t/cernsso
Author: Alexander Baranov
Author-email: sashab1@yandex-team.ru
License: UNKNOWN
Platform: UNKNOWN
Requires-Dist: sh (==1.11)
